build_dashboard/__init__.py
build_dashboard/__main__.py
build_dashboard/cli.py
build_dashboard/model.py
build_dashboard/screen.py
build_dashboard/views.py
build_dashboard-0.2.7.dist-info/LICENSE
build_dashboard-0.2.7.dist-info/METADATA
build_dashboard-0.2.7.dist-info/WHEEL
build_dashboard-0.2.7.dist-info/entry_points.txt
build_dashboard-0.2.7.dist-info/top_level.txt
build_dashboard-0.2.7.dist-info/RECORD
