Metadata-Version: 2.1
Name: build-dashboard
Version: 0.2.7
Summary: Buildbot CLI Dashboard
Home-page: https://github.com/ReverentEngineer/build-dashboard
Author: Jeffrey Hill
Author-email: jeff@reverentengineer.com
License: UNKNOWN
Keywords: buildbot,continuous integration,ci,cli
Platform: UNKNOWN
Classifier: Development Status :: 3 - Alpha
Classifier: Intended Audience :: Developers
Classifier: Topic :: Software Development :: Build Tools
Classifier: License :: OSI Approved :: Apache Software License
Classifier: Programming Language :: Python :: 3
License-File: LICENSE
Requires-Dist: aiohttp
Requires-Dist: toml
Requires-Dist: asciimatics
Requires-Dist: cachetools
